spider_xhs_mcp_server/__init__.py
spider_xhs_mcp_server/server.py
spider_xhs_mcp_server-0.1.0.dist-info/METADATA
spider_xhs_mcp_server-0.1.0.dist-info/WHEEL
spider_xhs_mcp_server-0.1.0.dist-info/entry_points.txt
spider_xhs_mcp_server-0.1.0.dist-info/RECORD
