Metadata-Version: 2.4
Name: spider-xhs-mcp-server
Version: 0.1.0
Summary: 小红书爬虫
Author-email: Melle_lichao <lichao10060909@163.com>
Requires-Python: >=3.11
Requires-Dist: mcp[cli]>=1.8.1
